odin_cli/chat_service_interface.py
odin_cli/cli.py
odin_cli/commands/__init__.py
odin_cli/commands/ask.py
odin_cli/commands/config.py
odin_cli/commands/run.py
odin_cli/plugins/__init__.py
odin_cli/plugins/bedrock.py
odin_cli/plugins/openai.py
odin_cli/tools.py
odin_cli/utils.py
odin_cli-0.0.16.dist-info/LICENSE
odin_cli-0.0.16.dist-info/METADATA
odin_cli-0.0.16.dist-info/WHEEL
odin_cli-0.0.16.dist-info/entry_points.txt
odin_cli-0.0.16.dist-info/RECORD
