Metadata-Version: 2.1
Name: odin-cli
Version: 0.0.16
Summary: An app for interacting with AI services
License: MIT
Author: Cliff Pyles
Author-email: cliff@cliffpyles.com
Requires-Python: >=3.9.0,<4.0.0
Classifier: Development Status :: 3 - Alpha
Classifier: License :: OSI Approved :: MIT License
Classifier: Operating System :: OS Independent
Classifier: Programming Language :: Python :: 3
Classifier: Programming Language :: Python :: 3.9
Classifier: Programming Language :: Python :: 3.10
Classifier: Programming Language :: Python :: 3.11
Classifier: Programming Language :: Python :: 3.12
Requires-Dist: boto3 (>=1.34.5,<2.0.0)
Requires-Dist: openai (>=1.6.0,<2.0.0)
Requires-Dist: prompt-toolkit (>=3.0.43,<4.0.0)
Requires-Dist: pydantic (>=2.5.3,<3.0.0)
Requires-Dist: python-frontmatter (>=1.0.1,<2.0.0)
Requires-Dist: pyyaml (>=6.0.1,<7.0.0)
Requires-Dist: requests (>=2.31.0,<3.0.0)
Project-URL: Homepage, https://github.com/cliffpyles/odin
Project-URL: Issues, https://github.com/cliffpyles/odin/issues
